atman_kg_nlp/__init__.py
atman_kg_nlp/_test/__init__.py
atman_kg_nlp/_test/atman_parser_test.py
atman_kg_nlp/_test/string_utils_test.py
atman_kg_nlp/preprocess/__init__.py
atman_kg_nlp/preprocess/_benepar.py
atman_kg_nlp/preprocess/_stanford_nlp.py
atman_kg_nlp/preprocess/model.py
atman_kg_nlp/preprocess/parser.py
atman_kg_nlp/string_utils/__init__.py
atman_kg_nlp/string_utils/trie.py
atman_kg_nlp-0.2.1.dist-info/LICENSE
atman_kg_nlp-0.2.1.dist-info/METADATA
atman_kg_nlp-0.2.1.dist-info/WHEEL
atman_kg_nlp-0.2.1.dist-info/top_level.txt
atman_kg_nlp-0.2.1.dist-info/RECORD
